src/flake8-trio/__init.py
flake8_trio-24.3.9.dist-info/METADATA
flake8_trio-24.3.9.dist-info/WHEEL
flake8_trio-24.3.9.dist-info/licenses/LICENSE
flake8_trio-24.3.9.dist-info/RECORD
