Metadata-Version: 2.1
Name: flake8-trio
Version: 24.3.9
Summary: Micropackage to redirect users to flake8-async.
Project-URL: Homepage, https://github.com/python-trio/flake8-async
Project-URL: Issues, https://github.com/python-trio/flake8-async/issues
Author: John Litborn
License-File: LICENSE
Classifier: Development Status :: 7 - Inactive
Classifier: License :: OSI Approved :: The Unlicense (Unlicense)
Classifier: Operating System :: OS Independent
Classifier: Programming Language :: Python :: 3
Requires-Python: >=3
Requires-Dist: flake8-async>=24.3.1
